metapredict/.DS_Store
metapredict/__init__.py
metapredict/_version.py
metapredict/meta.py
metapredict/metapredict_exceptions.py
metapredict/parameters.py
metapredict/analysis/caid1_and_2_disorder_pdb.fasta
metapredict/analysis/caid1_disorder_pdb.fasta
metapredict/analysis/caid2_analysis.py
metapredict/analysis/caid2_disorder_pdb.fasta
metapredict/analysis/seq_caid_plddt.tsv
metapredict/analysis/test_different_predictors.py
metapredict/backend/.DS_Store
metapredict/backend/architectures.py
metapredict/backend/creating_V2_and_V3_scores.py
metapredict/backend/data_structures.py
metapredict/backend/domain_definition.py
metapredict/backend/encode_sequence.py
metapredict/backend/meta_graph.py
metapredict/backend/meta_tools.py
metapredict/backend/network_parameters.py
metapredict/backend/predictor.py
metapredict/backend/cython/domain_definition.c
metapredict/backend/cython/domain_definition.cpython-38-darwin.so
metapredict/backend/cython/domain_definition.pyx
metapredict/backend/networks/.DS_Store
metapredict/backend/networks/epoch-49-step-42600.ckpt
metapredict/backend/networks/epoch023_val_loss1529.48.ckpt
metapredict/backend/networks/epoch029_val_loss791.84.ckpt
metapredict/backend/networks/epoch029_val_loss959.58.ckpt
metapredict/backend/networks/epoch096_val_loss1584.14.ckpt
metapredict/backend/networks/epoch099_val_loss1107.08.ckpt
metapredict/backend/networks/epoch179_val_loss1095.24.ckpt
metapredict/backend/networks/metaDisorder.pt
metapredict/backend/networks/meta_predict_disorder_100e_v1.pt
metapredict/backend/networks/metameta_2_7_22_nl2_hs20_b32_V3.pt
metapredict/backend/networks/metapredict_network_v2_200epochs_nl1_hs20.pt
metapredict/backend/networks/metapredict_network_v3_200epochs_nl2_hs20.pt
metapredict/backend/networks/non_bin_PAE_hs40_nl2.pt
metapredict/backend/networks/smoothed_v3_real_plddt_re.pt
metapredict/backend/ppLDDT/.DS_Store
metapredict/backend/ppLDDT/networks/alpha_fold_networkV7_hs100_nL2_200e_all_prot.pt
metapredict-3.0.1.dist-info/LICENSE
metapredict-3.0.1.dist-info/METADATA
metapredict-3.0.1.dist-info/WHEEL
metapredict-3.0.1.dist-info/entry_points.txt
metapredict-3.0.1.dist-info/top_level.txt
metapredict-3.0.1.dist-info/RECORD
