Metadata-Version: 2.1
Name: metapredict
Version: 3.0.1
Summary: A machine learning-based tool for predicting protein disorder.
Author-email: Ryan Emenecker <remenecker@wustl.edu>
License: MIT
Requires-Python: >=3.8
License-File: LICENSE
Requires-Dist: cython
Requires-Dist: torch
Requires-Dist: numpy
Requires-Dist: matplotlib
Requires-Dist: protfasta
Requires-Dist: scipy
Requires-Dist: urllib3
Requires-Dist: tqdm
Requires-Dist: pytorch-lightning
Requires-Dist: getSequence >=2.2.1
Provides-Extra: test
Requires-Dist: pytest >=6.1.2 ; extra == 'test'
